bashlex/__init__.py
bashlex/ast.py
bashlex/errors.py
bashlex/flags.py
bashlex/heredoc.py
bashlex/parser.py
bashlex/parsetab.py
bashlex/shutils.py
bashlex/state.py
bashlex/subst.py
bashlex/tokenizer.py
bashlex/utils.py
bashlex/yacc.py
bashlex-0.17.dist-info/LICENSE
bashlex-0.17.dist-info/METADATA
bashlex-0.17.dist-info/WHEEL
bashlex-0.17.dist-info/top_level.txt
bashlex-0.17.dist-info/RECORD
